Metadata-Version: 1.0
Name: pyPiEx
Version: 0.1
Summary: This is demo for python package creation
Home-page: https://github.com/pearlselvan/PyPiEx.git
Author: Muthu Selvan SR
Author-email: learnwin2020@gmail.com
License: MIT
Platform: UNKNOWN
